streamlit_card_component/__init__.py
streamlit_card_component/frontend/build/asset-manifest.json
streamlit_card_component/frontend/build/favicon.ico
streamlit_card_component/frontend/build/index.html
streamlit_card_component/frontend/build/logo192.png
streamlit_card_component/frontend/build/logo512.png
streamlit_card_component/frontend/build/manifest.json
streamlit_card_component/frontend/build/robots.txt
streamlit_card_component/frontend/build/static/css/main.6f7c73b6.css
streamlit_card_component/frontend/build/static/css/main.6f7c73b6.css.map
streamlit_card_component/frontend/build/static/js/main.d5c17306.js
streamlit_card_component/frontend/build/static/js/main.d5c17306.js.LICENSE.txt
streamlit_card_component/frontend/build/static/js/main.d5c17306.js.map
streamlit_card_component-2.0.0.dist-info/METADATA
streamlit_card_component-2.0.0.dist-info/WHEEL
streamlit_card_component-2.0.0.dist-info/top_level.txt
streamlit_card_component-2.0.0.dist-info/RECORD
